marzano/__init__.py
marzano/cli.py
marzano/marzano.py
marzano-2019.2.14.dist-info/AUTHORS.rst
marzano-2019.2.14.dist-info/LICENSE
marzano-2019.2.14.dist-info/METADATA
marzano-2019.2.14.dist-info/WHEEL
marzano-2019.2.14.dist-info/entry_points.txt
marzano-2019.2.14.dist-info/top_level.txt
marzano-2019.2.14.dist-info/RECORD
