Metadata-Version: 2.1
Name: marzano
Version: 2019.2.14
Summary: Calculate predicted learning value from history of assessments using Marzano's Power Law
Home-page: https://github.com/sreyemnayr/marzano
Author: Ryan Meyers
Author-email: ryanmeyersweb@gmail.com
License: MIT license
Keywords: marzano
Platform: UNKNOWN
Classifier: Development Status :: 2 - Pre-Alpha
Classifier: Intended Audience :: Developers
Classifier: License :: OSI Approved :: MIT License
Classifier: Natural Language :: English
Classifier: Programming Language :: Python :: 2
Classifier: Programming Language :: Python :: 2.7
Classifier: Programming Language :: Python :: 3
Classifier: Programming Language :: Python :: 3.4
Classifier: Programming Language :: Python :: 3.5
Classifier: Programming Language :: Python :: 3.6
Classifier: Programming Language :: Python :: 3.7
Requires-Dist: Click (>=6.0)
